TornadoGailan/README.md
TornadoGailan/__init__.py
TornadoGailan/__main__.py
TornadoGailan/file.epub
TornadoGailan/index.html
TornadoGailan/css/__init__.py
TornadoGailan/css/annotations.css
TornadoGailan/css/main.css
TornadoGailan/css/normalize.css
TornadoGailan/css/popup.css
TornadoGailan/font/__init__.py
TornadoGailan/font/fontello.eot
TornadoGailan/font/fontello.svg
TornadoGailan/font/fontello.ttf
TornadoGailan/font/fontello.woff
TornadoGailan/img/__init__.py
TornadoGailan/img/annotator-glyph-sprite.png
TornadoGailan/img/annotator-icon-sprite.png
TornadoGailan/img/apple-touch-icon.png
TornadoGailan/img/cancelfullscreen.png
TornadoGailan/img/close.png
TornadoGailan/img/fullscreen.png
TornadoGailan/img/loader.gif
TornadoGailan/img/menu-icon.png
TornadoGailan/img/save.png
TornadoGailan/img/saved.png
TornadoGailan/img/settings-s.png
TornadoGailan/img/settings.png
TornadoGailan/img/star.png
TornadoGailan/js/__init__.py
TornadoGailan/js/epub.js
TornadoGailan/js/epub.min.js
TornadoGailan/js/epub.min.map
TornadoGailan/js/hooks.min.js
TornadoGailan/js/hooks.min.map
TornadoGailan/js/reader.js
TornadoGailan/js/reader.js.map
TornadoGailan/js/reader.min.js
TornadoGailan/js/reader.min.map
TornadoGailan/js/hooks/__init__.py
TornadoGailan/js/hooks/extensions/__init__.py
TornadoGailan/js/hooks/extensions/highlight.js
TornadoGailan/js/libs/__init__.py
TornadoGailan/js/libs/jquery.min.js
TornadoGailan/js/libs/localforage.min.js
TornadoGailan/js/libs/screenfull.js
TornadoGailan/js/libs/screenfull.min.js
TornadoGailan/js/libs/zip.min.js
TornadoGailan/js/plugins/__init__.py
TornadoGailan/js/plugins/hypothesis.js
TornadoGailan/js/plugins/search.js
tornado_gailan-2024.3.2.0.dist-info/METADATA
tornado_gailan-2024.3.2.0.dist-info/WHEEL
tornado_gailan-2024.3.2.0.dist-info/entry_points.txt
tornado_gailan-2024.3.2.0.dist-info/top_level.txt
tornado_gailan-2024.3.2.0.dist-info/RECORD
